README.md
setup.py
llmdet/__init__.py
llmdet/arguments.py
llmdet/classifier.py
llmdet/detector.py
llmdet/new_proxy_perplexity.py
llmdet/run_main.py
llmdet/train_classifier.py
llmdet/truth_perplexity.py
llmdet.egg-info/PKG-INFO
llmdet.egg-info/SOURCES.txt
llmdet.egg-info/dependency_links.txt
llmdet.egg-info/requires.txt
llmdet.egg-info/top_level.txt