Metadata-Version: 2.1
Name: llmdet
Version: 1.0.4
Summary: LLMDet: A Large Language Models Detection Tool
Home-page: https://github.com/cansee5/LLMDet
Author: Kangxi Wu, Liang Pang
Author-email: wukx0901@gmail.com
License: UNKNOWN
Platform: UNKNOWN
Classifier: Programming Language :: Python :: 3
Classifier: License :: OSI Approved :: MIT License
Classifier: Operating System :: OS Independent
Requires-Python: >=3.8
